{
  "bestHomeTeamPlayers": [
    {
      "value": "8.0",
      "label": "rating",
      "player": {
        "name": "Jurriën Timber",
        "slug": "jurrien-timber",
        "shortName": "J. Timber",
        "position": "D",
        "jerseyNumber": "12",
        "height": 179,
        "userCount": 21703,
        "gender": "M",
        "sofascoreId": "jurrientimber",
        "id": 958959,
        "marketValueCurrency": "EUR",
        "dateOfBirthTimestamp": 992736000,
        "proposedMarketValueRaw": {
          "value": 73000000,
          "currency": "EUR"
        },
        "fieldTranslations": {
          "nameTranslation": {
            "ar": "يوريان تيمبر",
            "bn": "জুরিন টিম্বার",
            "hi": "जुरीएन टिम्बर"
          },
          "shortNameTranslation": {
            "ar": "ي. تيمبر",
            "bn": "জে. টিম্বার",
            "hi": "जे. टिम्बर"
          }
        }
      }
    },
    {
      "value": "7.9",
      "label": "rating",
      "player": {
        "name": "Myles Lewis-Skelly",
        "firstName": "Myles Lewis-Skelly",
        "slug": "lewis-skelly-myles",
        "shortName": "M. Lewis-Skelly",
        "position": "D",
        "jerseyNumber": "49",
        "height": 178,
        "userCount": 16307,
        "gender": "M",
        "sofascoreId": "myleslewisskelly",
        "id": 1423711,
        "marketValueCurrency": "EUR",
        "dateOfBirthTimestamp": 1159228800,
        "proposedMarketValueRaw": {
          "value": 43000000,
          "currency": "EUR"
        },
        "fieldTranslations": {
          "nameTranslation": {
            "ar": "لويس-سكيلي، مايلز",
            "bn": "লুইস-স্কেলি, মাইলস",
            "hi": "लुईस-स्केली, माइल्स"
          },
          "shortNameTranslation": {
            "ar": "م. لويس-سكيلي",
            "bn": "এম. লুইস-স্কেলি",
            "hi": "एम. लुईस-स्केली"
          }
        }
      }
    },
    {
      "value": "7.7",
      "label": "rating",
      "player": {
        "name": "Leandro Trossard",
        "slug": "leandro-trossard",
        "shortName": "L. Trossard",
        "position": "F",
        "jerseyNumber": "19",
        "height": 172,
        "userCount": 31338,
        "gender": "M",
        "sofascoreId": "leandrotrossard",
        "id": 135666,
        "marketValueCurrency": "EUR",
        "dateOfBirthTimestamp": 786499200,
        "proposedMarketValueRaw": {
          "value": 21000000,
          "currency": "EUR"
        },
        "fieldTranslations": {
          "nameTranslation": {
            "ar": "لياندرو تروسارد",
            "bn": "লিয়েন্দ্রো ট্রসার্ড",
            "hi": "लिएंड्रो ट्रोसार्ड"
          },
          "shortNameTranslation": {
            "ar": "ل. تروسارد",
            "bn": "এল. ট্রসার্ড",
            "hi": "एल. ट्रोसार्ड"
          }
        }
      }
    }
  ],
  "bestAwayTeamPlayers": [
    {
      "value": "7.2",
      "label": "rating",
      "player": {
        "name": "Dara O'Shea",
        "firstName": "",
        "lastName": "",
        "slug": "dara-oshea",
        "shortName": "D. O'Shea",
        "position": "D",
        "jerseyNumber": "26",
        "height": 188,
        "userCount": 659,
        "gender": "M",
        "id": 856719,
        "marketValueCurrency": "EUR",
        "dateOfBirthTimestamp": 920505600,
        "proposedMarketValueRaw": {
          "value": 15900000,
          "currency": "EUR"
        },
        "fieldTranslations": {
          "nameTranslation": {
            "ar": "دارا أوشيا",
            "bn": "দারা ও'শিয়া",
            "hi": "दारा ओ'शीया"
          },
          "shortNameTranslation": {
            "ar": "د. أوشيا",
            "bn": "ডি. ও'শিয়া",
            "hi": "डी. ओ'शीया"
          }
        }
      }
    },
    {
      "value": "7.2",
      "label": "rating",
      "player": {
        "name": "Arijanet Murić",
        "slug": "arijanet-muric",
        "shortName": "A. Murić",
        "position": "G",
        "jerseyNumber": "49",
        "height": 198,
        "userCount": 1933,
        "gender": "M",
        "id": 888971,
        "marketValueCurrency": "EUR",
        "dateOfBirthTimestamp": 910396800,
        "proposedMarketValueRaw": {
          "value": 6900000,
          "currency": "EUR"
        },
        "fieldTranslations": {
          "nameTranslation": {
            "ar": "أريجانيت موريش",
            "bn": "আরিজানেট মুরিচ",
            "hi": "अरिजानेट मुरिक"
          },
          "shortNameTranslation": {
            "ar": "أ. موريش",
            "bn": "এ. মুরিচ",
            "hi": "ए. मुरिक"
          }
        }
      }
    },
    {
      "value": "7.1",
      "label": "rating",
      "player": {
        "name": "Jacob Greaves",
        "slug": "jacob-greaves",
        "shortName": "J. Greaves",
        "position": "D",
        "jerseyNumber": "24",
        "height": 193,
        "userCount": 524,
        "gender": "M",
        "id": 990821,
        "marketValueCurrency": "EUR",
        "dateOfBirthTimestamp": 968716800,
        "proposedMarketValueRaw": {
          "value": 15300000,
          "currency": "EUR"
        },
        "fieldTranslations": {
          "nameTranslation": {
            "ar": "جاكوب غريفز"
          },
          "shortNameTranslation": {
            "ar": "ج. غريفز"
          }
        }
      }
    }
  ],
  "playerOfTheMatch": {
    "value": "8.0",
    "label": "rating",
    "player": {
      "name": "Jurriën Timber",
      "slug": "jurrien-timber",
      "shortName": "J. Timber",
      "position": "D",
      "jerseyNumber": "12",
      "height": 179,
      "userCount": 21703,
      "gender": "M",
      "sofascoreId": "jurrientimber",
      "id": 958959,
      "marketValueCurrency": "EUR",
      "dateOfBirthTimestamp": 992736000,
      "proposedMarketValueRaw": {
        "value": 73000000,
        "currency": "EUR"
      },
      "fieldTranslations": {
        "nameTranslation": {
          "ar": "يوريان تيمبر",
          "bn": "জুরিন টিম্বার",
          "hi": "जुरीएन टिम्बर"
        },
        "shortNameTranslation": {
          "ar": "ي. تيمبر",
          "bn": "জে. টিম্বার",
          "hi": "जे. टिम्बर"
        }
      }
    }
  }
}