{
  "shotmap": [
    {
      "player": {
        "name": "Jordan Lefort",
        "slug": "jordan-lefort",
        "shortName": "J. Lefort",
        "position": "D",
        "jerseyNumber": "21",
        "userCount": 183,
        "gender": "M",
        "id": 363042,
        "fieldTranslations": {
          "nameTranslation": {
            "ar": "جوردان ليفورت",
            "bn": "জর্ডান লেফোর্ট",
            "hi": "जॉर्डन लेफोर्ट"
          },
          "shortNameTranslation": {
            "ar": "ج. ليفورت",
            "bn": "জে. লেফর্ট",
            "hi": "जे. लेफोर्ट"
          }
        }
      },
      "isHome": true,
      "shotType": "save",
      "situation": "corner",
      "playerCoordinates": {
        "x": 6.6,
        "y": 54.9,
        "z": 0
      },
      "bodyPart": "head",
      "goalMouthLocation": "low-right",
      "goalMouthCoordinates": {
        "x": 0,
        "y": 47.6,
        "z": 15.8
      },
      "blockCoordinates": {
        "x": 1,
        "y": 52.2,
        "z": 0
      },
      "xg": 0.095578357577324,
      "xgot": 0.15029415488243,
      "goalkeeper": {
        "name": "Jonathan Fischer",
        "slug": "jonathan-fischer",
        "shortName": "J. Fischer",
        "position": "G",
        "jerseyNumber": "1",
        "userCount": 277,
        "gender": "M",
        "id": 1004550,
        "fieldTranslations": {
          "nameTranslation": {
            "ar": "جوناثان فيشر"
          },
          "shortNameTranslation": {
            "ar": "ج. فيشر"
          }
        }
      },
      "id": 6626244,
      "time": 55,
      "timeSeconds": 3253,
      "draw": {
        "start": {
          "x": 54.9,
          "y": 6.6
        },
        "block": {
          "x": 52.2,
          "y": 1
        },
        "end": {
          "x": 52.4,
          "y": 0
        },
        "goal": {
          "x": 52.4,
          "y": 84.2
        }
      },
      "reversedPeriodTime": 36,
      "reversedPeriodTimeSeconds": 2147,
      "periodTimeSeconds": 553,
      "incidentType": "shot"
    }
  ]
}