{
  "homeManager": {
    "name": "Ruben den Uil",
    "slug": "ruben-den-uil",
    "shortName": "R. d. Uil",
    "id": 805588,
    "fieldTranslations": {
      "nameTranslation": {
        "ar": "روبين دين أيل"
      },
      "shortNameTranslation": {
        "ar": "ر. د. أيل"
      }
    }
  },
  "awayManager": {
    "name": "Robin van Persie",
    "slug": "robin-van-persie",
    "shortName": "R. v. Persie",
    "id": 801864,
    "fieldTranslations": {
      "nameTranslation": {
        "ar": "روبن فان بيرسي"
      },
      "shortNameTranslation": {
        "ar": "ر. ف. بيرسي"
      }
    }
  }
}