{
  "shotmap": [
    {
      "player": {
        "name": "Davide Zappacosta",
        "slug": "davide-zappacosta",
        "shortName": "D. Zappacosta",
        "position": "M",
        "jerseyNumber": "77",
        "userCount": 2188,
        "gender": "M",
        "id": 132318,
        "fieldTranslations": {
          "nameTranslation": {
            "ar": "دافيدي زاباكوستا",
            "bn": "ডেভিড জাপ্পাকোস্টা",
            "hi": "डेविड ज़प्पाकोस्टा"
          },
          "shortNameTranslation": {
            "ar": "د. زاباكوستا",
            "bn": "ডি. জাপ্পাকোস্টা",
            "hi": "डी. ज़प्पाकोस्टा"
          }
        }
      },
      "isHome": true,
      "shotType": "goal",
      "goalType": "regular",
      "situation": "assisted",
      "playerCoordinates": {
        "x": 4.8,
        "y": 67.8,
        "z": 0
      },
      "bodyPart": "left-foot",
      "goalMouthLocation": "low-left",
      "goalMouthCoordinates": {
        "x": 0,
        "y": 53.6,
        "z": 7.6
      },
      "xg": 0.068054512143135,
      "xgot": 0.31508174538612,
      "goalkeeper": {
        "name": "Emil Audero",
        "slug": "emil-audero",
        "shortName": "E. Audero",
        "position": "G",
        "jerseyNumber": "1",
        "userCount": 10760,
        "gender": "M",
        "id": 318603,
        "fieldTranslations": {
          "nameTranslation": {
            "ar": "إميل أوديرو",
            "bn": "এমিল অডেরো",
            "hi": "एमिल औडेरो"
          },
          "shortNameTranslation": {
            "ar": "إ. أوديرو",
            "bn": "ই. অডেরো",
            "hi": "ई. औडेरो"
          }
        }
      },
      "id": 6680771,
      "time": 25,
      "timeSeconds": 1472,
      "draw": {
        "start": {
          "x": 67.8,
          "y": 4.8
        },
        "end": {
          "x": 46.4,
          "y": 0
        },
        "goal": {
          "x": 46.4,
          "y": 92.4
        }
      },
      "reversedPeriodTime": 21,
      "reversedPeriodTimeSeconds": 1228,
      "periodTimeSeconds": 1472,
      "incidentType": "shot"
    }
  ]
}