{
  "shotmap": [
    {
      "player": {
        "name": "Jeremy Toljan",
        "slug": "jeremy-toljan",
        "shortName": "J. Toljan",
        "position": "D",
        "jerseyNumber": "22",
        "userCount": 374,
        "gender": "M",
        "id": 149606,
        "fieldTranslations": {
          "nameTranslation": {
            "ar": "جيريمي توليان",
            "bn": "জেরেমি টলজান",
            "hi": "जेरेमी टोलजन"
          },
          "shortNameTranslation": {
            "ar": "ج. توليان",
            "bn": "জে. টলজান",
            "hi": "जे. टोलजन"
          }
        }
      },
      "isHome": true,
      "shotType": "miss",
      "situation": "regular",
      "playerCoordinates": {
        "x": 23.2,
        "y": 37.3,
        "z": 0
      },
      "bodyPart": "right-foot",
      "goalMouthLocation": "high",
      "goalMouthCoordinates": {
        "x": 0,
        "y": 46.4,
        "z": 94.4
      },
      "xg": 0.031465366482735,
      "xgot": 0,
      "goalkeeper": {
        "name": "Jan Oblak",
        "slug": "jan-oblak",
        "shortName": "J. Oblak",
        "position": "G",
        "jerseyNumber": "13",
        "userCount": 12399,
        "gender": "M",
        "sofascoreId": "oblakjan",
        "id": 69768,
        "fieldTranslations": {
          "nameTranslation": {
            "ar": "يان أوبلاك",
            "bn": "জন ওব্লাক",
            "hi": "जान ओबलाक"
          },
          "shortNameTranslation": {
            "ar": "ي. أوبلاك",
            "bn": "জে. ওব্লাক",
            "hi": "जे. ओबलाक"
          }
        }
      },
      "id": 6617936,
      "time": 71,
      "timeSeconds": 4217,
      "draw": {
        "start": {
          "x": 37.3,
          "y": 23.2
        },
        "end": {
          "x": 53.6,
          "y": 0
        },
        "goal": {
          "x": 53.6,
          "y": 5.6
        }
      },
      "reversedPeriodTime": 20,
      "reversedPeriodTimeSeconds": 1183,
      "periodTimeSeconds": 1517,
      "incidentType": "shot"
    }
  ]
}