{
  "predictions": {
    "yellowCards": 5,
    "corners": 10,
    "bothTeamsToScore": false,
    "homeNormaltimeScore": 1,
    "awayNormaltimeScore": 0,
    "winningProbability": {
      "home": 46,
      "draw": 30,
      "away": 24
    },
    "possibleResultsMatrix": [
      [
        0.13438326211813,
        0.10583660618969,
        0.041677017781818,
        0.010941228961133,
        0.0021542536669722,
        0.00033932633185167
      ],
      [
        0.16412164422822,
        0.12925774797845,
        0.050899945254103,
        0.013362471327716,
        0.0026309798432883,
        0.00041441764871335
      ],
      [
        0.10022049502153,
        0.078930938991534,
        0.031081931538788,
        0.0081597616053155,
        0.0016066016370112,
        0.00025306315992031
      ],
      [
        0.040799605965411,
        0.032132661175169,
        0.01265340546516,
        0.003321826121464,
        0.00065404500066937,
        0.0001030216145599
      ],
      [
        0.012457091585224,
        0.0098108668861995,
        0.0038633861042212,
        0.0010142326438237,
        0.00019969551865533,
        3.1454952994357e-05
      ],
      [
        0.0030427574402401,
        0.0023963930913536,
        0.00094366704561144,
        0.00024773550888794,
        4.8777439020507e-05,
        7.6831571479743e-06
      ]
    ]
  },
  "sections": [
    {
      "subtitle": "Current Form",
      "text": "Sunderland's last 5 matches show mixed results with 1 win, 2 draws, and 2 losses, indicating inconsistency, though they managed a late draw against Arsenal. Newcastle United, on the other hand, are unbeaten in their last 4 matches, securing 2 wins and 2 draws, with a strong attacking output as seen in their 4-1 victory over Everton. Their recent form suggests they have momentum heading into this clash."
    },
    {
      "subtitle": "Head-to-Head Record",
      "text": "In the last two head-to-head encounters, Newcastle dominated with a 3-0 win in January 2024 at Sunderland's home, while the 2016 match ended in a 1-1 draw. Sunderland historically struggles to convert chances against Newcastle, as seen in their lack of big chances in the latest matchup."
    },
    {
      "subtitle": "Season Statistics",
      "text": "Sunderland, positioned 10th with 23 points, have scored 18 goals but underperformed their xG by nearly 5 goals, indicating finishing issues. Newcastle, 12th with 22 points, have scored 21 goals and shown better attacking intent, often creating big chances (as seen in recent games). Defensively, both teams concede similarly, with Sunderland at 17 and Newcastle at 19 goals conceded this season."
    },
    {
      "subtitle": "Key Players and Tactics",
      "text": "Sunderland's Wilson Isidor (4 goals) and Daniel Ballard (strong defensively with 70.3% ground duels won) will be crucial, likely focusing on counter-attacks given their low possession stats (42% average). Newcastle’s Bruno Guimarães (5 goals, 7.39 rating) and Anthony Gordon (3 goals in last 5 matches) are in fine form, suggesting an aggressive approach with high pressing and corners (average over 10.5 per game)."
    },
    {
      "subtitle": "Match Outlook",
      "text": "Based on Sofascore’s prediction (46% home win, 30% draw, 24% away win) and Newcastle’s superior form and attacking output, this match at the Stadium of Light is likely to be competitive. Sunderland’s home advantage and defensive resilience could pose a challenge, but Newcastle’s recent scoring streak and key player form tilt the balance slightly in their favor."
    }
  ],
  "halftimePredictions": {
    "nextTeamToScore": {
      "name": "Sunderland",
      "slug": "sunderland",
      "shortName": "Sunderland",
      "gender": "M",
      "sport": {
        "name": "Football",
        "slug": "football",
        "id": 1
      },
      "userCount": 206469,
      "nameCode": "SUN",
      "disabled": false,
      "national": false,
      "type": 0,
      "id": 41,
      "teamColors": {
        "primary": "#ffffff",
        "secondary": "#ca0000",
        "text": "#ca0000"
      },
      "fieldTranslations": {
        "nameTranslation": {
          "ar": "سندرلاند",
          "ru": "АФК Сандерленд"
        },
        "shortNameTranslation": {}
      }
    },
    "playerToScore": {
      "name": "Daniel Ballard",
      "firstName": "",
      "lastName": "",
      "slug": "ballard-daniel",
      "shortName": "D. Ballard",
      "position": "D",
      "jerseyNumber": "5",
      "userCount": 4668,
      "gender": "M",
      "id": 958878,
      "fieldTranslations": {
        "nameTranslation": {
          "ar": "دانيال بالارد",
          "bn": "ব্যালার্ড, ড্যানিয়েল",
          "hi": "बैलार्ड, डैनियल"
        },
        "shortNameTranslation": {
          "ar": "د. بالارد",
          "bn": "ডি. ব্যালার্ড",
          "hi": "डी. बैलार्ड"
        }
      }
    },
    "secondHalfOverOneAndAHalfGoals": false,
    "homeNormaltimeScore": 1,
    "awayNormaltimeScore": 0
  },
  "halftimeSections": [
    {
      "subtitle": "Half-time overview",
      "text": "The first half of the Tyne-Wear derby between Sunderland and Newcastle United at the Stadium of Light ended in a goalless draw. Sunderland dominated possession and showed more intent in the attacking third, creating a big chance but failing to convert. Newcastle, on the other hand, had limited opportunities but managed to keep a tight defensive structure, restricting Sunderland’s ability to turn their dominance into goals. Both teams displayed physicality in duels, with neither side gaining a clear upper hand in aerial or ground battles."
    },
    {
      "subtitle": "Sunderland's attacking intent",
      "text": "Sunderland showcased their intent to control the game through sustained periods in the final third. They managed several entries into the penalty area and won possession in dangerous positions multiple times. Despite creating a notable opportunity, their finishing let them down, with a big chance missed. The home side will be looking to capitalize on their territorial advantage in the second half and turn their pressure into goals."
    },
    {
      "subtitle": "Newcastle's defensive resilience",
      "text": "Newcastle United adopted a more cautious approach in the first half, focusing on defensive solidity. They limited Sunderland’s clear-cut chances despite being on the back foot for much of the half. Their entries into the final third were fewer, and they struggled to win possession in advanced areas. However, their backline held firm, ensuring they go into the break level. The away side will need to find more attacking impetus if they hope to take something from this game."
    },
    {
      "subtitle": "Attack momentum analysis",
      "text": "The game began with a brief spell of attacking intent from Newcastle in the opening minutes, but Sunderland quickly took over, establishing a prolonged period of dominance with consistent pressure in the attacking areas. This momentum continued for the majority of the first half, with multiple waves of attacks from the home side. Towards the middle of the half, Newcastle managed to push back with a few sustained attacking spells of their own, gaining some foothold in the game. However, as the half drew to a close, Sunderland regained control with renewed energy, finishing the half on the front foot."
    },
    {
      "subtitle": "Disciplinary concerns",
      "text": "Discipline could play a role in the second half, particularly for Sunderland, who picked up a couple of yellow cards in the first 45 minutes. This may force them to temper their aggression to avoid further bookings or a potential sending-off. Newcastle, meanwhile, have kept a clean slate in terms of cards, which could allow them to press with more intensity as the game progresses."
    },
    {
      "subtitle": "Key players to watch",
      "text": "For Sunderland, Granit Xhaka has been influential in creating opportunities, showing composure in midfield with key passes and a high expected assists contribution. Daniel Ballard also poses a threat from set pieces, having come close in the first half. On Newcastle’s side, Nick Woltemade has been their most dangerous outlet, registering a shot on target, while Sandro Tonali and Dan Burn have been pivotal in maintaining defensive stability with crucial clearances."
    }
  ],
  "modelName": "Grok3"
}