{
  "homeManager": {
    "name": "Marco Rose",
    "slug": "marco-rose",
    "shortName": "M. Rose",
    "id": 193,
    "fieldTranslations": {
      "nameTranslation": {
        "ar": "ماركو روز",
        "hi": "मार्को रोज़",
        "bn": "মার্কো রোজ"
      },
      "shortNameTranslation": {
        "ar": "م. روز",
        "hi": "एम. रोज़",
        "bn": "এম. রোজ"
      }
    }
  },
  "awayManager": {
    "name": "Edin Terzić",
    "slug": "edin-terzic",
    "shortName": "E. Terzić",
    "id": 795257,
    "fieldTranslations": {
      "nameTranslation": {
        "ar": "إدين تيرزيتش",
        "hi": "एडिन टेरज़िक",
        "bn": "এডিন তেরজিচ"
      },
      "shortNameTranslation": {
        "ar": "إ. تيرزيتش",
        "hi": "ई. टेरज़िक",
        "bn": "ই. টেরজিক"
      }
    }
  }
}