{
  "shotmap": [
    {
      "player": {
        "name": "Aymen Sliti",
        "slug": "aymen-sliti",
        "shortName": "A. Sliti",
        "position": "M",
        "jerseyNumber": "32",
        "userCount": 961,
        "gender": "M",
        "id": 1479467,
        "fieldTranslations": {
          "nameTranslation": {
            "ar": "أيمن سليتي"
          },
          "shortNameTranslation": {
            "ar": "أ. سليتي"
          }
        }
      },
      "isHome": true,
      "shotType": "block",
      "situation": "corner",
      "playerCoordinates": {
        "x": 18.3,
        "y": 51.9,
        "z": 0
      },
      "bodyPart": "left-foot",
      "goalMouthLocation": "low-centre",
      "goalMouthCoordinates": {
        "x": 0,
        "y": 49,
        "z": 19
      },
      "blockCoordinates": {
        "x": 8.1,
        "y": 51.4,
        "z": 0
      },
      "xg": 0.025214498862624,
      "xgot": 0,
      "goalkeeper": {
        "name": "Jari De Busser",
        "slug": "jari-de-busser",
        "shortName": "J. D. Busser",
        "position": "G",
        "jerseyNumber": "22",
        "userCount": 296,
        "gender": "M",
        "id": 837072,
        "fieldTranslations": {
          "nameTranslation": {
            "ar": "ياري دي بوسر"
          },
          "shortNameTranslation": {
            "ar": "ي. دي بوسر"
          }
        }
      },
      "id": 6715704,
      "time": 62,
      "timeSeconds": 3715,
      "draw": {
        "start": {
          "x": 51.9,
          "y": 18.3
        },
        "block": {
          "x": 51.4,
          "y": 8.1
        },
        "end": {
          "x": 51,
          "y": 0
        },
        "goal": {
          "x": 51,
          "y": 81
        }
      },
      "reversedPeriodTime": 29,
      "reversedPeriodTimeSeconds": 1685,
      "periodTimeSeconds": 1015,
      "incidentType": "shot"
    },
    {
      "player": {
        "name": "Aymen Sliti",
        "slug": "aymen-sliti",
        "shortName": "A. Sliti",
        "position": "M",
        "jerseyNumber": "32",
        "userCount": 961,
        "gender": "M",
        "id": 1479467,
        "fieldTranslations": {
          "nameTranslation": {
            "ar": "أيمن سليتي"
          },
          "shortNameTranslation": {
            "ar": "أ. سليتي"
          }
        }
      },
      "isHome": true,
      "shotType": "block",
      "situation": "corner",
      "playerCoordinates": {
        "x": 21.4,
        "y": 46.6,
        "z": 0
      },
      "bodyPart": "left-foot",
      "goalMouthLocation": "low-left",
      "goalMouthCoordinates": {
        "x": 0,
        "y": 53.7,
        "z": 19
      },
      "blockCoordinates": {
        "x": 19.4,
        "y": 46.6,
        "z": 0
      },
      "xg": 0.017075335606933,
      "xgot": 0,
      "goalkeeper": {
        "name": "Jari De Busser",
        "slug": "jari-de-busser",
        "shortName": "J. D. Busser",
        "position": "G",
        "jerseyNumber": "22",
        "userCount": 296,
        "gender": "M",
        "id": 837072,
        "fieldTranslations": {
          "nameTranslation": {
            "ar": "ياري دي بوسر"
          },
          "shortNameTranslation": {
            "ar": "ي. دي بوسر"
          }
        }
      },
      "id": 6715499,
      "time": 52,
      "timeSeconds": 3087,
      "draw": {
        "start": {
          "x": 46.6,
          "y": 21.4
        },
        "block": {
          "x": 46.6,
          "y": 19.4
        },
        "end": {
          "x": 46.3,
          "y": 0
        },
        "goal": {
          "x": 46.3,
          "y": 81
        }
      },
      "reversedPeriodTime": 39,
      "reversedPeriodTimeSeconds": 2313,
      "periodTimeSeconds": 387,
      "incidentType": "shot"
    }
  ]
}